boldi/_ctx_version.py
boldi/ctx.py
boldi_ctx-0.9.7.dist-info/METADATA
boldi_ctx-0.9.7.dist-info/WHEEL
boldi_ctx-0.9.7.dist-info/RECORD
