Metadata-Version: 2.4
Name: boldi-ctx
Version: 0.9.7
Summary: boldi.ctx part of Boldi's Python libraries
Author-email: Boldizsár Palotás <boldizsar.palotas@gmail.com>
License: MIT
Requires-Python: >=3.10
Requires-Dist: boldi-proc==0.9.7
Provides-Extra: dev
Requires-Dist: typing-extensions; extra == 'dev'
